nomics_api/__init__.py
nomics_api/nomic_api.py
nomics_api-0.2.dist-info/LICENSE
nomics_api-0.2.dist-info/METADATA
nomics_api-0.2.dist-info/WHEEL
nomics_api-0.2.dist-info/top_level.txt
nomics_api-0.2.dist-info/RECORD
